puma/__init__.py
puma/version.py
puma/apps/__init__.py
puma/apps/android/__init__.py
puma/apps/android/appium_actions.py
puma/apps/android/google_camera/__init__.py
puma/apps/android/google_camera/google_camera.py
puma/apps/android/google_chrome/__init__.py
puma/apps/android/google_chrome/google_chrome.py
puma/apps/android/google_chrome/states.py
puma/apps/android/google_chrome/xpaths.py
puma/apps/android/google_maps/__init__.py
puma/apps/android/google_maps/google_maps.py
puma/apps/android/google_play_store/__init__.py
puma/apps/android/google_play_store/google_play_store.py
puma/apps/android/open_camera/__init__.py
puma/apps/android/open_camera/open_camera.py
puma/apps/android/snapchat/__init__.py
puma/apps/android/snapchat/snapchat.py
puma/apps/android/snapchat/xpaths.py
puma/apps/android/telegram/__init__.py
puma/apps/android/telegram/telegram.py
puma/apps/android/telegram/xpaths.py
puma/apps/android/teleguard/__init__.py
puma/apps/android/teleguard/teleguard.py
puma/apps/android/whatsapp/__init__.py
puma/apps/android/whatsapp/states.py
puma/apps/android/whatsapp/whatsapp.py
puma/apps/android/whatsapp/xpaths.py
puma/apps/android/whatsapp_business/__init__.py
puma/apps/android/whatsapp_business/whatsapp_business.py
puma/apps/android/whatsapp_business/whatsapp_common.py
puma/computer_vision/__init__.py
puma/computer_vision/ocr.py
puma/state_graph/__init__.py
puma/state_graph/action.py
puma/state_graph/app_template.py
puma/state_graph/popup_handler.py
puma/state_graph/puma_driver.py
puma/state_graph/state.py
puma/state_graph/state_graph.py
puma/state_graph/utils.py
puma/utils/__init__.py
puma/utils/debug.py
puma/utils/gtl_logging.py
puma/utils/route_simulator.py
puma/utils/video_utils.py
puma/utils/xpath_utils.py
pumapy-4.0.1.dist-info/licenses/LICENSE.txt
pumapy-4.0.1.dist-info/METADATA
pumapy-4.0.1.dist-info/WHEEL
pumapy-4.0.1.dist-info/top_level.txt
pumapy-4.0.1.dist-info/RECORD
