Metadata-Version: 2.4
Name: pumapy
Version: 4.0.1
Home-page: https://github.com/NetherlandsForensicInstitute/puma
Author: Netherlands Forensic Institute
Author-email: netherlandsforensicinstitute@users.noreply.github.com
License: EUPL-1.2
License-File: LICENSE.txt
Requires-Dist: urllib3~=2.5.0
Requires-Dist: appium-python-client~=4.3.0
Requires-Dist: Pillow==10.4.0
Requires-Dist: pytesseract==0.3.10
Requires-Dist: geopy~=2.4.1
Requires-Dist: setuptools~=80.9.0
Requires-Dist: gpxpy~=1.6.2
Requires-Dist: adb_pywrapper~=1.0.4
Requires-Dist: requests~=2.32.3
Dynamic: author
Dynamic: author-email
Dynamic: description
Dynamic: description-content-type
Dynamic: home-page
Dynamic: license
Dynamic: license-file
Dynamic: requires-dist
